annize/features/authors.py
annize/features/branding.py
annize/features/imprint.py
annize/features/keywords.py
annize/features/licensing.py
annize/features/media_galleries.py
annize/features/version.py
annize/features/_pidev/common.py
annize/features/_pidev/i18n.py
annize/features/_pidev/-data/icons/android.png
annize/features/_pidev/-data/icons/apache.png
annize/features/_pidev/-data/icons/archlinux.png
annize/features/_pidev/-data/icons/artwork.png
annize/features/_pidev/-data/icons/centos.png
annize/features/_pidev/-data/icons/database.png
annize/features/_pidev/-data/icons/debian.png
annize/features/_pidev/-data/icons/django.png
annize/features/_pidev/-data/icons/fedora.png
annize/features/_pidev/-data/icons/firefox.png
annize/features/_pidev/-data/icons/gentoo.png
annize/features/_pidev/-data/icons/git.png
annize/features/_pidev/-data/icons/gtk.png
annize/features/_pidev/-data/icons/java.png
annize/features/_pidev/-data/icons/javascript.png
annize/features/_pidev/-data/icons/jquery.png
annize/features/_pidev/-data/icons/kde.png
annize/features/_pidev/-data/icons/library.png
annize/features/_pidev/-data/icons/linux.png
annize/features/_pidev/-data/icons/misc.png
annize/features/_pidev/-data/icons/nullicon.png
annize/features/_pidev/-data/icons/opensuse.png
annize/features/_pidev/-data/icons/package.png
annize/features/_pidev/-data/icons/python.png
annize/features/_pidev/-data/icons/qt.png
annize/features/_pidev/-data/icons/question.png
annize/features/_pidev/-data/icons/redhat.png
annize/features/_pidev/-data/icons/settings.png
annize/features/_pidev/-data/icons/ssh.png
annize/features/_pidev/-data/icons/svn.png
annize/features/_pidev/-data/icons/ubuntu.png
annize/features/_pidev/-data/icons/w3.png
annize/features/_pidev/-data/icons/xfce.png
annize/features/_pidev/-data/icons/docrender/api_class.png
annize/features/_pidev/-data/icons/docrender/api_data.png
annize/features/_pidev/-data/icons/docrender/api_function.png
annize_pidev-1.0.6.dist-info/METADATA
annize_pidev-1.0.6.dist-info/WHEEL
annize_pidev-1.0.6.dist-info/top_level.txt
annize_pidev-1.0.6.dist-info/RECORD
