Metadata-Version: 2.4
Name: annize_pidev
Version: 1.0.6
Summary: a collection of Annize Features for software development tasks
Home-page: https://pseudopolis.eu/pino/annize_pidev
Author: Josef Hahn
Author-email: annize@pseudopolis.eu
License: AGPL 3
Keywords: python software development documentation packaging deployment build ci
Requires-Dist: annize~=7.0
Dynamic: author
Dynamic: author-email
Dynamic: description
Dynamic: description-content-type
Dynamic: home-page
Dynamic: keywords
Dynamic: license
Dynamic: requires-dist
Dynamic: summary
